src/gates.v
`timescale 1ns/1ps

// ========================================
// NAND素子の定義(これを最小単位とする)
// ========================================
module nand_gate (
    input a,
    input b,
    output y
);

    //nand(y,a,b); // 本篇    <----- コメントアウト
    
    // MOSFET版 番外篇    <----- 追加
    supply1 VDD; // 電源
    supply0 GND; // 接地

    // PMOS: a または b が 低電圧 なら y を 高電圧 に引き上げ
    pmos p1 (y, VDD, a);
    pmos p2 (y, VDD, b);

    // NMOS: a と b が両方 高電圧 なら y を 低電圧 に引き下げ
    nmos n1 (y, net1, a);
    nmos n2 (net1, GND, b);
    
endmodule

// ========================================
// NOT素子
// ========================================
module not_gate (
    input a, // 入力
    output y // 出力
);

    nand_gate u_not (
        .a(a), // 入力aをNANDのAに繋ぐ
        .b(a), // 同じくNANDのBにも繋ぐ
        .y(y)
    );

endmodule

// ========================================
// AND素子
// ========================================
module and_gate (
    input a,
    input b,
    output y
);

    wire n;
    nand_gate g1(a, b, n); // 一つ目のNANDの出力を
    nand_gate g2(n, n, y); // NOTに繋ぐ(NANDの入力両方に繋ぐ)
endmodule

// ========================================
// OR素子
// ========================================
module or_gate (
    input a,
    input b,
    output y
);
    wire not_a;
    wire not_b;
    
    nand_gate u_not_a(a, a, not_a); // aを反転(NAND入力2本共a)
    nand_gate u_not_b(b, b, not_b); // bを反転(NAND入力2本共b)
    
    nand_gate nand_nota_notb(not_a, not_b, y); // NOT(a)とNOT(b)をNAND→OR
endmodule

// ========================================
// XOR素子
// ========================================
module xor_gate (
    input a,
    input b,
    output y
);

    wire n1; // A NAND B
    wire n2; // A NAND n1
    wire n3; // B NAND n1
    
    nand_gate g1(a, b, n1);
    nand_gate g2(a, n1, n2);
    nand_gate g3(n1, b, n3);
    nand_gate g4(n2, n3, y);

endmodule

src/dff.v
`timescale 1ns/1ps

module d_ff (
    input  d,
    input  clk,
    output q,
    output q_n
);
    wire d_n;
    wire nand1_out;
    wire nand2_out;

    not_gate inv (.a(d), .y(d_n));
    nand_gate nand1 (.a(d),   .b(clk), .y(nand1_out));
    nand_gate nand2 (.a(d_n), .b(clk), .y(nand2_out));
    nand_gate nand3 (.a(nand1_out), .b(q_n), .y(q));
    nand_gate nand4 (.a(nand2_out), .b(q),   .y(q_n));

endmodule

sim/tb_dff.v
`timescale 1ns/1ps

module tb_dff;
    reg d;
    reg clk;
    wire q;
    wire q_n;

    d_ff uut (
        .d(d),
        .clk(clk),
        .q(q),
        .q_n(q_n)
    );

    // クロック生成（周期20ns）
    always #10 clk = ~clk;

    // 波形ダンプ（GTKWaveしたいとき用）
    initial begin
        $dumpfile("wave.vcd");
        $dumpvars(0, tb_dff);
    end

    initial begin
        $monitor("t=%0t | clk=%b d=%b | q=%b q_n=%b", $time, clk, d, q, q_n);

        // 初期化
        clk = 0;
        d = 0;
        #5;

        // clk=0 の間に d を変えてもホールド
        d = 1;  #5;   // clk=0
        #10;         // clk=1 に → d=1 を透過 → q=1

        // clk=1 の間に d を変える → そのまま追随（ラッチだから）
        d = 0;  #5;   // q=0 になる
        d = 1;  #5;   // q=1 になる

        // clk=0 に戻す → ホールド
        #10;         // clk=0
        d = 0;  #10; // 変えても q は変わらない
        d = 1;  #10;

        // もう一回 clk=1
        #10;         // clk=1 → d=1 を捕捉
        d = 0;  #10; // clk=1 のまま → q=0 に追随

        $finish;
    end
endmodule

wave.vcd
$date
	Wed Sep 30 20:43:31 2026
$end
$version
	Icarus Verilog
$end
$timescale
	1ps
$end
$scope module tb_dff $end
$var wire 1 ! q $end
$var wire 1 " q_n $end
$var reg 1 # clk $end
$var reg 1 $ d $end
$scope module uut $end
$var wire 1 # clk $end
$var wire 1 $ d $end
$var wire 1 % d_n $end
$var wire 1 & nand1_out $end
$var wire 1 ' nand2_out $end
$var wire 1 ! q $end
$var wire 1 " q_n $end
$scope module inv $end
$var wire 1 $ a $end
$var wire 1 % y $end
$scope module u_not $end
$var wire 1 ( GND $end
$var wire 1 ) VDD $end
$var wire 1 $ a $end
$var wire 1 $ b $end
$var wire 1 * net1 $end
$var wire 1 % y $end
$upscope $end
$upscope $end
$scope module nand1 $end
$var wire 1 + GND $end
$var wire 1 , VDD $end
$var wire 1 $ a $end
$var wire 1 # b $end
$var wire 1 - net1 $end
$var wire 1 & y $end
$upscope $end
$scope module nand2 $end
$var wire 1 . GND $end
$var wire 1 / VDD $end
$var wire 1 % a $end
$var wire 1 # b $end
$var wire 1 0 net1 $end
$var wire 1 ' y $end
$upscope $end
$scope module nand3 $end
$var wire 1 1 GND $end
$var wire 1 2 VDD $end
$var wire 1 & a $end
$var wire 1 " b $end
$var wire 1 3 net1 $end
$var wire 1 ! y $end
$upscope $end
$scope module nand4 $end
$var wire 1 4 GND $end
$var wire 1 5 VDD $end
$var wire 1 ' a $end
$var wire 1 ! b $end
$var wire 1 6 net1 $end
$var wire 1 " y $end
$upscope $end
$upscope $end
$upscope $end
$enddefinitions $end
#0
$dumpvars
x6
15
04
x3
12
01
z0
1/
0.
z-
1,
0+
z*
1)
0(
1'
1&
1%
0$
0#
x"
x!
$end
#5000
0%
0*
1$
#10000
z3
0"
06
1!
0&
0-
00
1#
#20000
1%
z*
0$
1&
z-
z0
0#
#25000
0%
0*
1$
#30000
0&
0-
00
1#
#40000
1%
z*
0$
1&
z-
z0
0#
#50000
0%
0*
0&
1$
0-
06
1!
z3
0"
1'
00
1#
#60000
1&
z-
z0
0#
#70000
z6
0!
03
1"
0'
1%
z*
0$
1&
0-
00
1#
#80000
z-
1'
z0
0#
