src/gates.v
`timescale 1ns/1ps

// ========================================
// NAND素子の定義(これを最小単位とする)
// ========================================
module nand_gate (
    input a,
    input b,
    output y
);

    //nand(y,a,b); // 本篇    <----- コメントアウト
    
    // MOSFET版 番外篇    <----- 追加
    supply1 VDD; // 電源
    supply0 GND; // 接地

    // PMOS: a または b が 低電圧 なら y を 高電圧 に引き上げ
    pmos p1 (y, VDD, a);
    pmos p2 (y, VDD, b);

    // NMOS: a と b が両方 高電圧 なら y を 低電圧 に引き下げ
    nmos n1 (y, net1, a);
    nmos n2 (net1, GND, b);
    
endmodule

// ========================================
// NOT素子
// ========================================
module not_gate (
    input a, // 入力
    output y // 出力
);

    nand_gate u_not (
        .a(a), // 入力aをNANDのAに繋ぐ
        .b(a), // 同じくNANDのBにも繋ぐ
        .y(y)
    );

endmodule

// ========================================
// AND素子
// ========================================
module and_gate (
    input a,
    input b,
    output y
);

    wire n;
    nand_gate g1(a, b, n); // 一つ目のNANDの出力を
    nand_gate g2(n, n, y); // NOTに繋ぐ(NANDの入力両方に繋ぐ)
endmodule

// ========================================
// OR素子
// ========================================
module or_gate (
    input a,
    input b,
    output y
);
    wire not_a;
    wire not_b;
    
    nand_gate u_not_a(a, a, not_a); // aを反転(NAND入力2本共a)
    nand_gate u_not_b(b, b, not_b); // bを反転(NAND入力2本共b)
    
    nand_gate nand_nota_notb(not_a, not_b, y); // NOT(a)とNOT(b)をNAND→OR
endmodule

// ========================================
// XOR素子
// ========================================
module xor_gate (
    input a,
    input b,
    output y
);

    wire n1; // A NAND B
    wire n2; // A NAND n1
    wire n3; // B NAND n1
    
    nand_gate g1(a, b, n1);
    nand_gate g2(a, n1, n2);
    nand_gate g3(n1, b, n3);
    nand_gate g4(n2, n3, y);

endmodule

src/muxs.v
module mux2_1 (
    input a,
    input b,
    input sel,
    output y
);

    wire nsel;
    wire w1;
    wire w2;

    not_gate u_not (
        .a(sel),
        .y(nsel)
    );

    and_gate u_and1 (
        .a(a),
        .b(nsel),
        .y(w1)
    );

    and_gate u_and2 (
        .a(b),
        .b(sel),
        .y(w2)
    );

    or_gate u_or (
        .a(w1),
        .b(w2),
        .y(y)
    );

endmodule

sim/tb_mux2_1.v
`timescale 1ns/1ps

module tb_mux2_1;
    reg  a, b;
    reg  sel;
    wire y;

    mux2_1 uut (
        .a(a),
        .b(b),
        .sel(sel),
        .y(y)
    );

    initial begin
        $dumpfile("wave_mux2_1.vcd");
        $dumpvars(0, tb_mux2_1);

        $display("Time | a | b | sel | y");
        $monitor("%4t | %b | %b |  %b  | %b",
                  $time, a, b, sel, y);

        // sel=0 → a が出力されるはず
        a = 1'b0; b = 1'b0; sel = 1'b0; #10;
        a = 1'b1; b = 1'b0; sel = 1'b0; #10;
        a = 1'b0; b = 1'b1; sel = 1'b0; #10;
        a = 1'b1; b = 1'b1; sel = 1'b0; #10;

        // sel=1 → b が出力されるはず
        a = 1'b0; b = 1'b0; sel = 1'b1; #10;
        a = 1'b1; b = 1'b0; sel = 1'b1; #10;
        a = 1'b0; b = 1'b1; sel = 1'b1; #10;
        a = 1'b1; b = 1'b1; sel = 1'b1; #10;

        $finish;
    end
endmodule

wave_mux2_1.vcd
$date
	Sun Sep 27 20:57:11 2026
$end
$version
	Icarus Verilog
$end
$timescale
	1ps
$end
$scope module tb_mux2_1 $end
$var wire 1 ! y $end
$var reg 1 " a $end
$var reg 1 # b $end
$var reg 1 $ sel $end
$scope module uut $end
$var wire 1 " a $end
$var wire 1 # b $end
$var wire 1 $ sel $end
$var wire 1 ! y $end
$var wire 1 % w2 $end
$var wire 1 & w1 $end
$var wire 1 ' nsel $end
$scope module u_and1 $end
$var wire 1 " a $end
$var wire 1 & y $end
$var wire 1 ( n $end
$var wire 1 ' b $end
$scope module g1 $end
$var wire 1 " a $end
$var wire 1 ( y $end
$var wire 1 ' b $end
$upscope $end
$scope module g2 $end
$var wire 1 ( a $end
$var wire 1 ( b $end
$var wire 1 & y $end
$upscope $end
$upscope $end
$scope module u_and2 $end
$var wire 1 # a $end
$var wire 1 $ b $end
$var wire 1 % y $end
$var wire 1 ) n $end
$scope module g1 $end
$var wire 1 # a $end
$var wire 1 $ b $end
$var wire 1 ) y $end
$upscope $end
$scope module g2 $end
$var wire 1 ) a $end
$var wire 1 ) b $end
$var wire 1 % y $end
$upscope $end
$upscope $end
$scope module u_not $end
$var wire 1 $ a $end
$var wire 1 ' y $end
$scope module u_not $end
$var wire 1 $ a $end
$var wire 1 $ b $end
$var wire 1 ' y $end
$upscope $end
$upscope $end
$scope module u_or $end
$var wire 1 & a $end
$var wire 1 % b $end
$var wire 1 ! y $end
$var wire 1 * not_b $end
$var wire 1 + not_a $end
$scope module nand_nota_notb $end
$var wire 1 ! y $end
$var wire 1 * b $end
$var wire 1 + a $end
$upscope $end
$scope module u_not_a $end
$var wire 1 & a $end
$var wire 1 & b $end
$var wire 1 + y $end
$upscope $end
$scope module u_not_b $end
$var wire 1 % a $end
$var wire 1 % b $end
$var wire 1 * y $end
$upscope $end
$upscope $end
$upscope $end
$upscope $end
$enddefinitions $end
#0
$dumpvars
1+
1*
1)
1(
1'
0&
0%
0$
0#
0"
0!
$end
#10000
1!
0+
1&
0(
1"
#20000
0!
1+
0&
1(
1#
0"
#30000
1!
0+
1&
0(
1"
#40000
0!
1+
0&
0'
1(
1$
0#
0"
#50000
1"
#60000
1!
0*
1%
0)
1#
0"
#70000
1"
